langextract_azureopenai/__init__.py
langextract_azureopenai/provider.py
langextract_azureopenai/schema.py
langextract_azureopenai-0.1.7.dist-info/METADATA
langextract_azureopenai-0.1.7.dist-info/WHEEL
langextract_azureopenai-0.1.7.dist-info/entry_points.txt
langextract_azureopenai-0.1.7.dist-info/licenses/LICENSE
langextract_azureopenai-0.1.7.dist-info/RECORD
