Metadata-Version: 2.4
Name: langextract-azureopenai
Version: 0.1.7
Summary: LangExtract provider plugin for Azure OpenAI
Project-URL: Homepage, https://github.com/google/langextract
Project-URL: Documentation, https://github.com/google/langextract/blob/main/README.md
Project-URL: Repository, https://github.com/google/langextract
Project-URL: Bug Tracker, https://github.com/google/langextract/issues
Project-URL: Changelog, https://github.com/google/langextract/releases
Author: LangExtract Contributors
Maintainer: LangExtract Contributors
License-Expression: Apache-2.0
License-File: LICENSE
Keywords: azure-openai,extraction,langextract,llm,nlp,openai,plugin,provider
Classifier: Development Status :: 4 - Beta
Classifier: Intended Audience :: Developers
Classifier: License :: OSI Approved :: Apache Software License
Classifier: Operating System :: OS Independent
Classifier: Programming Language :: Python :: 3
Classifier: Programming Language :: Python :: 3.10
Classifier: Programming Language :: Python :: 3.11
Classifier: Programming Language :: Python :: 3.12
Classifier: Programming Language :: Python :: 3.13
Classifier: Topic :: Scientific/Engineering :: Artificial Intelligence
Classifier: Topic :: Software Development :: Libraries :: Python Modules
Classifier: Topic :: Text Processing :: Linguistic
Requires-Python: >=3.10
Requires-Dist: langextract>=1.0.0
Requires-Dist: openai>=1.0.0
Provides-Extra: dev
Requires-Dist: black>=22.0.0; extra == 'dev'
Requires-Dist: isort>=5.0.0; extra == 'dev'
Requires-Dist: mypy>=1.0.0; extra == 'dev'
Requires-Dist: pytest-asyncio>=0.21.0; extra == 'dev'
Requires-Dist: pytest-cov>=4.0.0; extra == 'dev'
Requires-Dist: pytest-mock>=3.10.0; extra == 'dev'
Requires-Dist: pytest>=7.0; extra == 'dev'
Requires-Dist: ruff>=0.1.0; extra == 'dev'
Provides-Extra: docs
Requires-Dist: mkdocs-gen-files>=0.4.0; extra == 'docs'
Requires-Dist: mkdocs-literate-nav>=0.5.0; extra == 'docs'
Requires-Dist: mkdocs-material>=8.5.0; extra == 'docs'
Requires-Dist: mkdocs-section-index>=0.3.0; extra == 'docs'
Requires-Dist: mkdocs>=1.4.0; extra == 'docs'
Provides-Extra: test
Requires-Dist: pytest-asyncio>=0.21.0; extra == 'test'
Requires-Dist: pytest-mock>=3.10.0; extra == 'test'
Requires-Dist: pytest>=7.0; extra == 'test'
